plone.intelligenttext-4.0.2-py3.13-nspkg.pth
plone/intelligenttext/README.rst
plone/intelligenttext/__init__.py
plone/intelligenttext/tests.py
plone/intelligenttext/transforms.py
plone_intelligenttext-4.0.2.dist-info/METADATA
plone_intelligenttext-4.0.2.dist-info/WHEEL
plone_intelligenttext-4.0.2.dist-info/namespace_packages.txt
plone_intelligenttext-4.0.2.dist-info/top_level.txt
plone_intelligenttext-4.0.2.dist-info/RECORD
